SudokuWizard/__init__.py
SudokuWizard/exceptions.py
SudokuWizard/main.py
SudokuWizard/sudoku_algorithms.py
SudokuWizard/sudoku_wizard.py
SudokuWizard/res/photos/numbers/number1HQ_nomargin.jpg
SudokuWizard/res/photos/numbers/number2HQ_nomargin.jpg
SudokuWizard/res/photos/numbers/number3HQ_nomargin.jpg
SudokuWizard/res/photos/numbers/number4HQ_nomargin.jpg
SudokuWizard/res/photos/numbers/number5HQ_nomargin.jpg
SudokuWizard/res/photos/numbers/number6HQ_nomargin.jpg
SudokuWizard/res/photos/numbers/number7HQ_nomargin.jpg
SudokuWizard/res/photos/numbers/number8HQ_nomargin.jpg
SudokuWizard/res/photos/numbers/number9HQ_nomargin.jpg
sudokuwizard-0.0.1.dist-info/LICENSE
sudokuwizard-0.0.1.dist-info/METADATA
sudokuwizard-0.0.1.dist-info/WHEEL
sudokuwizard-0.0.1.dist-info/top_level.txt
sudokuwizard-0.0.1.dist-info/RECORD
