Metadata-Version: 2.1
Name: sudokuwizard
Version: 0.0.1
Summary: Simple program to solve Sudoku puzzles only with the source image.
Home-page: https://github.com/INIGO-7/sudokuwizard
Author: G.Guillotine - (INIGO-7 on GitHub)
Author-email: your-email@example.com
Classifier: Development Status :: 4 - Beta
Classifier: Intended Audience :: Developers
Classifier: Topic :: Software Development :: Libraries :: Python Modules
Classifier: License :: OSI Approved :: MIT License
Classifier: Programming Language :: Python :: 3
Classifier: Programming Language :: Python :: 3.6
Classifier: Programming Language :: Python :: 3.7
Classifier: Programming Language :: Python :: 3.8
Classifier: Programming Language :: Python :: 3.9
Classifier: Programming Language :: Python :: 3.10
Requires-Python: >=3.6
License-File: LICENSE
Requires-Dist: opencv-python
Requires-Dist: pandas
Requires-Dist: numpy
Requires-Dist: imutils
Requires-Dist: scikit-image
Requires-Dist: easyocr
